{
  "projects": {
    "gto-wizard-clone": {
      "last_reviewed_sha": "503b7fa",
      "last_reviewed_at": "2026-06-26T19:05:00Z",
      "verdict": "pending",
      "health": "build_passes_53_vitest_clean_build_study_matrix_readability",
      "tests_pass": "53/53 vitest, 368/368 python, playwright --list works",
      "deployment_url": "https://wiz.codeovertcp.com",
      "deployment_status": "200_OK_0_JS_ERRORS_SB_FIX_CONFIRMED",
      "phase": 2,
      "current_task": "fix-dashboard-hero-polish",
      "all_coach_tasks_done": false,
      "spec_gaps_open": 2,
      "spec_gaps_total": 3,
      "note": "Tick 2026-06-26T19:05 UTC. fix-study-matrix-readability complete (503b7fa). Font sizes increased, freq chips improved. Coach pending."
    },
    "polytopia-clone": {
      "last_reviewed_sha": "5c7bf4f",
      "last_reviewed_at": "2026-06-26T12:35:00Z",
      "verdict": "approved",
      "health": "515_tests_pass_0_regressions_build_clean_tech_tree_enhanced",
      "tests_pass": "515/515 vitest",
      "deployment_url": "https://hex.codeovertcp.com",
      "deployment_status": "200_OK_PHASER_SELECT_SCENE_GAME_SCENE",
      "phase": 2,
      "current_task": "fix-city-building-visual-improvements",
      "all_coach_tasks_done": false,
      "spec_gaps_open": 2,
      "spec_gaps_total": 2,
      "note": "Tick 2026-06-26 20:10 UTC: fix-tech-tree-visualization \u2014 dependency edges, progress bars, category filter tabs. 515 tests pass, build clean. Next: fix-city-building-visual-improvements.",
      "last_sha": "914395d",
      "consecutive_on_project": 3
    }
  },
  "last_run": "2026-06-26T10:10:00Z",
  "note": "Tick 2026-06-26 20:10 UTC. Polytopia: fix-tech-tree-visualization complete (914395d). Enhanced with dependency edges, progress bars, category filters. 515 tests pass, build clean. Next: fix-city-building-visual-improvements.",
  "consecutive_on_project": 3,
  "active_project": "polytopia-clone"
}
